<?xml version="1.0" encoding="UTF-8"?>
<objects serializationModel="Studio.02.01.00">
	<object class="AudioFile" id="{cbdaa308-1574-4b41-b527-974e30dc72fe}">
		<property name="assetPath">
			<value>S-5.mp3</value>
		</property>
		<property name="frequencyInKHz">
			<value>48</value>
		</property>
		<property name="channelCount">
			<value>2</value>
		</property>
		<property name="length">
			<value>0.45600000000000002</value>
		</property>
		<relationship name="masterAssetFolder">
			<destination>{920b5d7c-f5cf-4320-a28c-23e85022d416}</destination>
		</relationship>
	</object>
</objects>
